parcyl.py
Parcyl-1.0a4.dist-info/LICENSE
Parcyl-1.0a4.dist-info/METADATA
Parcyl-1.0a4.dist-info/WHEEL
Parcyl-1.0a4.dist-info/entry_points.txt
Parcyl-1.0a4.dist-info/top_level.txt
Parcyl-1.0a4.dist-info/RECORD
