Metadata-Version: 2.1
Name: Parcyl
Version: 1.0a4
Summary: UNKNOWN
Home-page: https://github.com/nicfit/Parcyl
Author: Travis Shirk
Author-email: travis@pobox.com
License: UNKNOWN
Platform: UNKNOWN
Classifier: Development Status :: 3 - Alpha
Provides-Extra: requirements
Requires-Dist: pip-tools ; extra == 'requirements'
